{
	"info": {
		"_postman_id": "b47186d4-7324-4a74-b562-847d4e329e3d",
		"name": "e_commerce",
		"schema": "https://schema.getpostman.com/json/collection/v2.1.0/collection.json",
		"_exporter_id": "25719203",
		"_collection_link": "https://dark-comet-762759.postman.co/workspace/Team-Workspace~b71bf4b5-5260-4610-8857-df160dadcef4/collection/25719203-b47186d4-7324-4a74-b562-847d4e329e3d?action=share&source=collection_link&creator=25719203"
	},
	"item": [
		{
			"name": "post Product",
			"request": {
				"method": "POST",
				"header": [],
				"body": {
					"mode": "raw",
					"raw": "{\r\n    \"name\":\"Dell XPS 16\",\r\n    \"price\": 1400,\r\n    \"categoryId\": 3\r\n    \r\n}",
					"options": {
						"raw": {
							"language": "json"
						}
					}
				},
				"url": {
					"raw": "http://localhost:8090/api/products/addProductByCategory/2",
					"protocol": "http",
					"host": [
						"localhost"
					],
					"port": "8090",
					"path": [
						"api",
						"products",
						"addProductByCategory",
						"2"
					]
				}
			},
			"response": []
		},
		{
			"name": "post Category",
			"request": {
				"method": "POST",
				"header": [],
				"body": {
					"mode": "raw",
					"raw": "{\r\n    \"name\":\"Laptop\"  \r\n}",
					"options": {
						"raw": {
							"language": "json"
						}
					}
				},
				"url": {
					"raw": "http://localhost:8090/api/categories",
					"protocol": "http",
					"host": [
						"localhost"
					],
					"port": "8090",
					"path": [
						"api",
						"categories"
					]
				}
			},
			"response": []
		},
		{
			"name": "get all Products",
			"protocolProfileBehavior": {
				"disableBodyPruning": true
			},
			"request": {
				"method": "GET",
				"header": [],
				"body": {
					"mode": "raw",
					"raw": "",
					"options": {
						"raw": {
							"language": "json"
						}
					}
				},
				"url": {
					"raw": "http://localhost:8090/api/products",
					"protocol": "http",
					"host": [
						"localhost"
					],
					"port": "8090",
					"path": [
						"api",
						"products"
					]
				}
			},
			"response": []
		},
		{
			"name": "get all Catego",
			"protocolProfileBehavior": {
				"disableBodyPruning": true
			},
			"request": {
				"method": "GET",
				"header": [],
				"body": {
					"mode": "raw",
					"raw": "",
					"options": {
						"raw": {
							"language": "json"
						}
					}
				},
				"url": {
					"raw": "http://localhost:8090/api/categories",
					"protocol": "http",
					"host": [
						"localhost"
					],
					"port": "8090",
					"path": [
						"api",
						"categories"
					]
				}
			},
			"response": []
		},
		{
			"name": "get Product By ID",
			"protocolProfileBehavior": {
				"disableBodyPruning": true
			},
			"request": {
				"method": "GET",
				"header": [],
				"body": {
					"mode": "raw",
					"raw": "",
					"options": {
						"raw": {
							"language": "json"
						}
					}
				},
				"url": {
					"raw": "http://localhost:8090/api/products/112",
					"protocol": "http",
					"host": [
						"localhost"
					],
					"port": "8090",
					"path": [
						"api",
						"products",
						"112"
					]
				}
			},
			"response": []
		},
		{
			"name": "get category By ID",
			"protocolProfileBehavior": {
				"disableBodyPruning": true
			},
			"request": {
				"method": "GET",
				"header": [],
				"body": {
					"mode": "raw",
					"raw": "",
					"options": {
						"raw": {
							"language": "json"
						}
					}
				},
				"url": {
					"raw": "http://localhost:8090/api/categories/2",
					"protocol": "http",
					"host": [
						"localhost"
					],
					"port": "8090",
					"path": [
						"api",
						"categories",
						"2"
					]
				}
			},
			"response": []
		},
		{
			"name": "Update Product By ID",
			"request": {
				"method": "PUT",
				"header": [],
				"body": {
					"mode": "raw",
					"raw": "{\r\n    \"id\": 112,\r\n    \"name\": \"Dell XPS 16\",\r\n    \"price\": 1389.0,\r\n    \"category\": {\r\n        \"id\": 2,\r\n        \"name\": \"Phone\"\r\n    },\r\n    \"cart\": []\r\n}",
					"options": {
						"raw": {
							"language": "json"
						}
					}
				},
				"url": {
					"raw": "http://localhost:8090/api/products/112",
					"protocol": "http",
					"host": [
						"localhost"
					],
					"port": "8090",
					"path": [
						"api",
						"products",
						"112"
					]
				}
			},
			"response": []
		},
		{
			"name": "Update categories By ID",
			"request": {
				"method": "PUT",
				"header": [],
				"body": {
					"mode": "raw",
					"raw": "{\r\n    \"id\": 2,\r\n    \"name\": \"Phone _ Mobile\"\r\n}",
					"options": {
						"raw": {
							"language": "json"
						}
					}
				},
				"url": {
					"raw": "http://localhost:8090/api/categories/2",
					"protocol": "http",
					"host": [
						"localhost"
					],
					"port": "8090",
					"path": [
						"api",
						"categories",
						"2"
					]
				}
			},
			"response": []
		},
		{
			"name": "delete Product By ID",
			"request": {
				"method": "DELETE",
				"header": [],
				"body": {
					"mode": "raw",
					"raw": "",
					"options": {
						"raw": {
							"language": "json"
						}
					}
				},
				"url": {
					"raw": "http://localhost:8090/api/products/104",
					"protocol": "http",
					"host": [
						"localhost"
					],
					"port": "8090",
					"path": [
						"api",
						"products",
						"104"
					]
				}
			},
			"response": []
		},
		{
			"name": "get Product By name",
			"protocolProfileBehavior": {
				"disableBodyPruning": true
			},
			"request": {
				"method": "GET",
				"header": [],
				"body": {
					"mode": "raw",
					"raw": "",
					"options": {
						"raw": {
							"language": "json"
						}
					}
				},
				"url": {
					"raw": "http://localhost:8090/api/products/byName?name=h",
					"protocol": "http",
					"host": [
						"localhost"
					],
					"port": "8090",
					"path": [
						"api",
						"products",
						"byName"
					],
					"query": [
						{
							"key": "name",
							"value": "h"
						}
					]
				}
			},
			"response": []
		}
	]
}